nonebot_plugin_report_manager/__init__.py
nonebot_plugin_report_manager/blacklist.py
nonebot_plugin_report_manager-0.5.0.dist-info/LICENSE
nonebot_plugin_report_manager-0.5.0.dist-info/METADATA
nonebot_plugin_report_manager-0.5.0.dist-info/WHEEL
nonebot_plugin_report_manager-0.5.0.dist-info/top_level.txt
nonebot_plugin_report_manager-0.5.0.dist-info/RECORD
