Metadata-Version: 2.1
Name: nonebot-plugin-report-manager
Version: 0.5.0
Summary: 群员通过Bot对话超管
Home-page: https://github.com/HauKuen/nonebot_plugin_report_manager
Author: HauKuen
Author-email: haukuen@foxmail.com
License: MIT License
Platform: all
Classifier: Intended Audience :: Developers
Classifier: Operating System :: OS Independent
Classifier: Natural Language :: Chinese (Simplified)
Classifier: Programming Language :: Python
Classifier: Programming Language :: Python :: Implementation
Classifier: Programming Language :: Python :: 3.8
Classifier: Programming Language :: Python :: 3.9
Classifier: Programming Language :: Python :: 3.10
Classifier: Topic :: Software Development :: Libraries
Requires-Python: >=3.8
License-File: LICENSE
Requires-Dist: nonebot2 <3.0.0,>=2.0.0rc1
Requires-Dist: nonebot-adapter-onebot >=2.1.5
